Metadata-Version: 2.1
Name: topsis-hiten
Version: 2.0.0
Summary: A Python package to implement Topsis analysis
Home-page: https://github.com/hitengarg45/topsis-hiten-101703234
Author: Hiten Garg
Author-email: hitengarg20@gmail.com
License: MIT
Platform: UNKNOWN
Classifier: License :: OSI Approved :: MIT License
Classifier: Programming Language :: Python :: 3
Classifier: Programming Language :: Python :: 3.7
